{
    "data": {
        "unit": "px",
        "page": {
            "width": 791,
            "height": 1120,
            "pages": 1,
            "xOffset": 0,
            "yOffset": 0,
            "title": "",
            "background": "#ffffff",
            "backgroundImage": "",
            "backgroundRepeat": "full",
            "backgroundWidth": 0,
            "backgroundHeight": 0,
            "backgroundXOffset": 0,
            "backgroundYOffset": 0
        },
        "groups": [],
        "elements": [
            {
                "id": "e_53",
                "type": "image",
                "props": {
                    "readonly": true,
                    "x": 32,
                    "y": 55,
                    "width": 300,
                    "height": 300,
                    "rotate": 0,
                    "alpha": 1,
                    "image": "//img-qn-5.51miz.com/preview/element/00/01/25/29/E-1252976-DA5E56E5.jpg!/quality/90/unsharp/true/compress/true/format/jpg/fh/400",
                    "bind": {
                        "tag": "",
                        "id": "",
                        "fields": []
                    },
                    "rotateX": false,
                    "rotateY": false,
                    "ename": "图片"
                }
            },
            {
                "id": "e_54",
                "type": "repeat",
                "props": {
                    "readonly": true,
                    "x": 412,
                    "y": 61,
                    "width": 313,
                    "height": 430,
                    "rotate": 0,
                    "alpha": 1,
                    "image": "//img-qn-0.51miz.com/preview/element/00/01/25/36/E-1253688-4BFE1D15.jpg!/quality/90/unsharp/true/compress/true/format/jpg/fh/400",
                    "bind": {
                        "tag": "",
                        "id": "",
                        "fields": []
                    },
                    "radius": 0,
                    "imageWidth": 102,
                    "imageHeight": 102,
                    "backgroundXOffset": 0,
                    "backgroundYOffset": 0,
                    "repeat": "repeat",
                    "ename": "平铺图"
                }
            },
            {
                "id": "e_55",
                "type": "barcode",
                "props": {
                    "readonly": true,
                    "x": 43,
                    "y": 436,
                    "width": 200,
                    "height": 80,
                    "rotate": 0,
                    "alpha": 1,
                    "text": "xinglie",
                    "bind": {
                        "tag": "",
                        "id": "",
                        "fields": []
                    },
                    "format": "code128",
                    "showText": true,
                    "color": "#000000",
                    "linewidth": 2,
                    "ename": "条形码"
                }
            },
            {
                "id": "e_56",
                "type": "hod-table",
                "props": {
                    "readonly": true,
                    "rows": [
                        {
                            "cols": [
                                {
                                    "height": 83,
                                    "width": 210,
                                    "bLeft": true,
                                    "bTop": true,
                                    "bRight": true,
                                    "bBottom": true,
                                    "rowspan": 1,
                                    "colspan": 1,
                                    "elements": [
                                        {
                                            "id": "e_57",
                                            "type": "text",
                                            "props": {
                                                "x": 15,
                                                "y": 32,
                                                "width": 200,
                                                "height": 25,
                                                "rotate": 0,
                                                "text": "",
                                                "bind": {
                                                    "tag": "",
                                                    "id": "",
                                                    "fields": []
                                                },
                                                "format": "",
                                                "fontsize": 14,
                                                "fontfamily": "tahoma",
                                                "alpha": 1,
                                                "letterspacing": 0,
                                                "background": "",
                                                "forecolor": "#000000",
                                                "styleBold": false,
                                                "styleUnderline": false,
                                                "styleItalic": false,
                                                "styleStrike": false,
                                                "styleOverline": false,
                                                "hpos": "flex-start",
                                                "vpos": "flex-start",
                                                "ename": "文本"
                                            }
                                        }
                                    ]
                                },
                                {
                                    "height": 83,
                                    "width": 150,
                                    "bLeft": true,
                                    "bTop": true,
                                    "bRight": true,
                                    "bBottom": true,
                                    "rowspan": 1,
                                    "colspan": 1,
                                    "elements": [
                                        {
                                            "id": "e_58",
                                            "type": "line",
                                            "props": {
                                                "readonly": true,
                                                "x": 3,
                                                "y": 44,
                                                "width": 200,
                                                "rotate": 0,
                                                "alpha": 1,
                                                "height": 1,
                                                "linetype": "solid",
                                                "color": "#000000",
                                                "ename": "直线"
                                            }
                                        }
                                    ]
                                }
                            ]
                        },
                        {
                            "cols": [
                                {
                                    "height": 30,
                                    "width": 210,
                                    "bLeft": true,
                                    "bTop": true,
                                    "bRight": true,
                                    "bBottom": true,
                                    "rowspan": 1,
                                    "colspan": 1,
                                    "elements": []
                                },
                                {
                                    "height": 30,
                                    "width": 150,
                                    "bLeft": true,
                                    "bTop": true,
                                    "bRight": true,
                                    "bBottom": true,
                                    "rowspan": 1,
                                    "colspan": 1,
                                    "elements": []
                                }
                            ]
                        }
                    ],
                    "x": 412,
                    "y": 576,
                    "width": 361,
                    "height": 114,
                    "alpha": 1,
                    "borderwidth": 1,
                    "bordertype": "solid",
                    "bordercolor": "#000000",
                    "borderdeed": "collapse",
                    "ename": "表格"
                }
            },
            {
                "id": "e_105",
                "type": "hod-hflex",
                "props": {
                    "rows": [
                        {
                            "height": 202,
                            "cols": [
                                {
                                    "width": 300,
                                    "elements": [
                                        {
                                            "id": "e_110",
                                            "type": "circle",
                                            "props": {
                                                "readonly": true,
                                                "x": 65,
                                                "y": 25,
                                                "width": 150,
                                                "height": 150,
                                                "rotate": 0,
                                                "alpha": 1,
                                                "borderwidth": 1,
                                                "bordertype": "solid",
                                                "bordercolor": "#000000",
                                                "fillcolor": "",
                                                "ename": "圆形"
                                            }
                                        }
                                    ],
                                    "borderLeftStyle": "solid",
                                    "borderLeftWidth": 1,
                                    "borderLeftTopRadius": 0,
                                    "borderRightTopRadius": 0,
                                    "borderLeftBottomRadius": 0,
                                    "borderRightBottomRadius": 0,
                                    "borderLeftColor": "#000000",
                                    "borderTopStyle": "solid",
                                    "borderTopWidth": 1,
                                    "borderTopColor": "#000000",
                                    "borderRightStyle": "solid",
                                    "borderRightWidth": 1,
                                    "borderRightColor": "#000000",
                                    "borderBottomStyle": "solid",
                                    "borderBottomWidth": 1,
                                    "borderBottomColor": "#000000"
                                }
                            ]
                        }
                    ],
                    "x": 77,
                    "y": 785,
                    "width": 300,
                    "height": 202,
                    "alpha": 1,
                    "ename": "H-Flex"
                }
            }
        ]
    },
    "success": true
}